{
  "main": {
    "id": "522c5fd7090ec0f4",
    "type": "split",
    "children": [
      {
        "id": "10f0414a118650e8",
        "type": "tabs",
        "children": [
          {
            "id": "0983cb352058371b",
            "type": "leaf",
            "pinned": true,
            "state": {
              "type": "markdown",
              "state": {
                "file": "日记/2022-11-17.md",
                "mode": "source",
                "backlinks": true,
                "source": true
              },
              "pinned": true
            },
            "group": "4671bd16c85efc3d"
          }
        ]
      },
      {
        "id": "0a3f872c062316ab",
        "type": "tabs",
        "children": [
          {
            "id": "30cf174c6de69cf8",
            "type": "leaf",
            "pinned": true,
            "state": {
              "type": "markdown",
              "state": {
                "file": "日记/2022-11-17.md",
                "mode": "source",
                "backlinks": true,
                "source": true
              },
              "pinned": true
            },
            "group": "4671bd16c85efc3d"
          }
        ]
      }
    ],
    "direction": "vertical"
  },
  "left": {
    "id": "e250aba2febb15e2",
    "type": "split",
    "children": [
      {
        "id": "9f8d472e69e423ce",
        "type": "tabs",
        "children": [
          {
            "id": "6fd2378fa717bd4e",
            "type": "leaf",
            "state": {
              "type": "starred",
              "state": {}
            }
          },
          {
            "id": "98cf98014b0730cd",
            "type": "leaf",
            "state": {
              "type": "file-explorer",
              "state": {
                "sortOrder": "alphabeticalReverse"
              }
            }
          },
          {
            "id": "716cd547a51022ea",
            "type": "leaf",
            "state": {
              "type": "search",
              "state": {
                "query": "tag:#Udtale",
                "matchingCase": true,
                "explainSearch": false,
                "collapseAll": false,
                "extraContext": true,
                "sortOrder": "byCreatedTime"
              }
            }
          }
        ],
        "currentTab": 1
      }
    ],
    "direction": "horizontal",
    "width": 277.5
  },
  "right": {
    "id": "4990d95c200463c3",
    "type": "split",
    "children": [
      {
        "id": "9becf11bdedf937f",
        "type": "tabs",
        "children": [
          {
            "id": "474186d86cb73568",
            "type": "leaf",
            "state": {
              "type": "calendar",
              "state": {}
            }
          },
          {
            "id": "856b579fa0f2b8b1",
            "type": "leaf",
            "state": {
              "type": "backlink",
              "state": {
                "file": "日记/2022-11-17.md",
                "collapseAll": false,
                "extraContext": false,
                "sortOrder": "alphabetical",
                "showSearch": false,
                "searchQuery": "",
                "backlinkCollapsed": false,
                "unlinkedCollapsed": true
              }
            }
          },
          {
            "id": "cfee9efd0e463dd6",
            "type": "leaf",
            "state": {
              "type": "outgoing-link",
              "state": {
                "file": "日记/2022-11-17.md",
                "linksCollapsed": false,
                "unlinkedCollapsed": true
              }
            }
          },
          {
            "id": "8232a35961c5e2fd",
            "type": "leaf",
            "state": {
              "type": "tag",
              "state": {
                "sortOrder": "alphabetical",
                "useHierarchy": true
              }
            }
          },
          {
            "id": "dc6f452f3fdb2ecc",
            "type": "leaf",
            "state": {
              "type": "outline",
              "state": {
                "file": "日记/2022-11-17.md"
              }
            }
          }
        ],
        "currentTab": 3
      }
    ],
    "direction": "horizontal",
    "width": 349.5,
    "collapsed": true
  },
  "active": "0983cb352058371b",
  "lastOpenFiles": [
    "日记/2022-11-16.md",
    "日记/2022-11-17.md",
    "日记/2022-11-16 2.md",
    "日记/2022-11-03.md",
    "Inbox/note.Apply for a permanent residence permit.md",
    "模板/NewWord 新单词模板.md",
    "模板/Dairy_日记模板.md",
    "模板/电费记录模板.md",
    "模板/笔记信息模板.md",
    "模板/待办事项列表.md"
  ]
}